fpdf-stubs/METADATA.toml
fpdf-stubs/__init__.pyi
fpdf-stubs/_fonttools_shims.pyi
fpdf-stubs/actions.pyi
fpdf-stubs/annotations.pyi
fpdf-stubs/bidi.pyi
fpdf-stubs/deprecation.pyi
fpdf-stubs/drawing.pyi
fpdf-stubs/encryption.pyi
fpdf-stubs/enums.pyi
fpdf-stubs/errors.pyi
fpdf-stubs/fonts.pyi
fpdf-stubs/fpdf.pyi
fpdf-stubs/graphics_state.pyi
fpdf-stubs/html.pyi
fpdf-stubs/image_datastructures.pyi
fpdf-stubs/image_parsing.pyi
fpdf-stubs/line_break.pyi
fpdf-stubs/linearization.pyi
fpdf-stubs/outline.pyi
fpdf-stubs/output.pyi
fpdf-stubs/pattern.pyi
fpdf-stubs/prefs.pyi
fpdf-stubs/py.typed
fpdf-stubs/recorder.pyi
fpdf-stubs/sign.pyi
fpdf-stubs/structure_tree.pyi
fpdf-stubs/svg.pyi
fpdf-stubs/syntax.pyi
fpdf-stubs/table.pyi
fpdf-stubs/template.pyi
fpdf-stubs/text_region.pyi
fpdf-stubs/transitions.pyi
fpdf-stubs/unicode_script.pyi
fpdf-stubs/util.pyi
types_fpdf2-2.8.4.20260130.dist-info/licenses/LICENSE
types_fpdf2-2.8.4.20260130.dist-info/METADATA
types_fpdf2-2.8.4.20260130.dist-info/WHEEL
types_fpdf2-2.8.4.20260130.dist-info/top_level.txt
types_fpdf2-2.8.4.20260130.dist-info/RECORD
